peachapisec.py
version.py
peachapisec_api-1.5.41.dist-info/LICENSE
peachapisec_api-1.5.41.dist-info/METADATA
peachapisec_api-1.5.41.dist-info/WHEEL
peachapisec_api-1.5.41.dist-info/top_level.txt
peachapisec_api-1.5.41.dist-info/RECORD
