Metadata-Version: 2.1
Name: peachapisec-api
Version: 1.5.41
Summary: Peach Web Proxy API module
Home-page: https://peach.tech
Author: Peach Tech
Author-email: support@peachfuzzer.com
License: Apache License 2.0
Keywords: peach fuzzing security test rest
Platform: UNKNOWN
Classifier: Development Status :: 5 - Production/Stable
Classifier: Intended Audience :: Developers
Classifier: License :: OSI Approved :: Apache Software License
Classifier: Operating System :: OS Independent
Classifier: Topic :: Security
Classifier: Topic :: Software Development :: Quality Assurance
Classifier: Topic :: Software Development :: Testing
Classifier: Topic :: Utilities
Classifier: Programming Language :: Python
Classifier: Programming Language :: Python :: 2
Classifier: Programming Language :: Python :: 3
Requires-Dist: requests (>=2.11)
Requires-Dist: semver (==2.8.1)
